<Properties StartupConfiguration="{2C63828C-E7B5-47A9-92B2-A9A05E117DA0}|Default">
  <MonoDevelop.Ide.Workbench ActiveDocument="CustomNativeApp/FirstPage.xaml">
    <Files>
      <File FileName="CustomNativeApp/FirstPage.xaml" Line="13" Column="1" />
      <File FileName="CustomNativeApp/FirstPage.xaml.cs" Line="13" Column="10" />
      <File FileName="CustomNativeApp/TestPage.cs" Line="7" Column="40" />
      <File FileName="CustomNativeApp/MyPage.cs" Line="7" Column="34" />
      <File FileName="CustomNativeApp/App.xaml" Line="5" Column="15" />
      <File FileName="CustomNativeApp/App.xaml.cs" Line="13" Column="13" />
    </Files>
  </MonoDevelop.Ide.Workbench>
  <MonoDevelop.Ide.Workspace ActiveConfiguration="Debug" />
  <MonoDevelop.Ide.DebuggingService.Breakpoints>
    <BreakpointStore />
  </MonoDevelop.Ide.DebuggingService.Breakpoints>
  <MonoDevelop.Ide.DebuggingService.PinnedWatches />
  <MonoDevelop.Ide.ItemProperties.CustomNativeApp.iOS PreferredExecutionTarget="MonoDevelop.IPhone.IPhoneSimulatorTarget.C358188E-6D34-43B6-8F28-9E4C588CDF41" />
  <MonoDevelop.Ide.ItemProperties.CustomNativeApp.Android PreferredExecutionTarget="Android.Android_Accelerated_Nougat" AndroidDesignerPreferredTheme="Theme.DeviceDefault.NoActionBar.Fullscreen" />
  <MultiItemStartupConfigurations />
</Properties>